MANIFEST.in
README.md
httmock.py
setup.py
httmock.egg-info/PKG-INFO
httmock.egg-info/SOURCES.txt
httmock.egg-info/dependency_links.txt
httmock.egg-info/requires.txt
httmock.egg-info/top_level.txt