Metadata-Version: 1.1
Name: httmock
Version: 1.0.2
Summary: A mocking library for requests.
Home-page: https://github.com/patrys/httmock
Author: Patryk Zawadzki
Author-email: patrys@room-303.com
License: Copyright 2013 Patryk Zawadzki
